{
  "map": "R06",
  "region": "johto",
  "land": {
    "rate": 20,
    "mons": [
      {
        "level": 13,
        "species": {
          "morn": "SPECIES_PIDGEY",
          "day": "SPECIES_PIDGEY",
          "nite": "SPECIES_ODDISH"
        }
      },
      {
        "level": 13,
        "species": {
          "morn": "SPECIES_BELLSPROUT",
          "day": "SPECIES_BELLSPROUT",
          "nite": {
            "HEARTGOLD": "SPECIES_ODDISH",
            "SOULSILVER": "SPECIES_MEOWTH"
          }
        }
      },
      {
        "level": 13,
        "species": {
          "morn": "SPECIES_PIDGEY",
          "day": "SPECIES_PIDGEY",
          "nite": "SPECIES_ODDISH"
        }
      },
      {
        "level": 13,
        "species": {
          "morn": "SPECIES_BELLSPROUT",
          "day": "SPECIES_BELLSPROUT",
          "nite": {
            "HEARTGOLD": "SPECIES_ODDISH",
            "SOULSILVER": "SPECIES_MEOWTH"
          }
        }
      },
      {
        "level": 14,
        "species": {
          "morn": {
            "HEARTGOLD": "SPECIES_PIDGEY",
            "SOULSILVER": "SPECIES_MEOWTH"
          },
          "day": {
            "HEARTGOLD": "SPECIES_PIDGEY",
            "SOULSILVER": "SPECIES_MEOWTH"
          },
          "nite": "SPECIES_BELLSPROUT"
        }
      },
      {
        "level": 14,
        "species": {
          "morn": {
            "HEARTGOLD": "SPECIES_PIDGEY",
            "SOULSILVER": "SPECIES_MEOWTH"
          },
          "day": {
            "HEARTGOLD": "SPECIES_PIDGEY",
            "SOULSILVER": "SPECIES_MEOWTH"
          },
          "nite": "SPECIES_BELLSPROUT"
        }
      },
      {
        "level": 15,
        "species": {
          "morn": "SPECIES_MAGNEMITE",
          "day": "SPECIES_MAGNEMITE",
          "nite": "SPECIES_MAGNEMITE"
        }
      },
      {
        "level": 15,
        "species": {
          "morn": "SPECIES_MAGNEMITE",
          "day": "SPECIES_MAGNEMITE",
          "nite": "SPECIES_MAGNEMITE"
        }
      },
      {
        "level": 12,
        "species": {
          "morn": "SPECIES_ABRA",
          "day": "SPECIES_ABRA",
          "nite": "SPECIES_ABRA"
        }
      },
      {
        "level": 14,
        "species": {
          "morn": "SPECIES_ABRA",
          "day": "SPECIES_ABRA",
          "nite": "SPECIES_ABRA"
        }
      },
      {
        "level": 12,
        "species": {
          "morn": "SPECIES_ABRA",
          "day": "SPECIES_ABRA",
          "nite": "SPECIES_ABRA"
        }
      },
      {
        "level": 14,
        "species": {
          "morn": "SPECIES_ABRA",
          "day": "SPECIES_ABRA",
          "nite": "SPECIES_ABRA"
        }
      }
    ]
  },
  "surf": {
    "rate": 15,
    "mons": [
      {
        "level": {
          "min": 10,
          "max": 10
        },
        "species": "SPECIES_PSYDUCK"
      },
      {
        "level": {
          "min": 5,
          "max": 5
        },
        "species": "SPECIES_PSYDUCK"
      },
      {
        "level": {
          "min": 10,
          "max": 10
        },
        "species": "SPECIES_GOLDUCK"
      },
      {
        "level": {
          "min": 10,
          "max": 10
        },
        "species": "SPECIES_GOLDUCK"
      },
      {
        "level": {
          "min": 10,
          "max": 10
        },
        "species": "SPECIES_GOLDUCK"
      }
    ]
  },
  "rock_smash": {
    "rate": 0,
    "mons": []
  },
  "fishing": {
    "old_rod": {
      "rate": 25,
      "mons": [
        {
          "level": {
            "min": 10,
            "max": 10
          },
          "species": "SPECIES_MAGIKARP"
        },
        {
          "level": {
            "min": 10,
            "max": 10
          },
          "species": "SPECIES_MAGIKARP"
        },
        {
          "level": {
            "min": 10,
            "max": 10
          },
          "species": "SPECIES_MAGIKARP"
        },
        {
          "level": {
            "min": 10,
            "max": 10
          },
          "species": "SPECIES_POLIWAG"
        },
        {
          "level": {
            "min": 10,
            "max": 10
          },
          "species": "SPECIES_POLIWAG"
        }
      ]
    },
    "good_rod": {
      "rate": 50,
      "mons": [
        {
          "level": {
            "min": 20,
            "max": 20
          },
          "species": "SPECIES_MAGIKARP"
        },
        {
          "level": {
            "min": 20,
            "max": 20
          },
          "species": "SPECIES_POLIWAG"
        },
        {
          "level": {
            "min": 20,
            "max": 20
          },
          "species": "SPECIES_POLIWAG"
        },
        {
          "level": {
            "min": 20,
            "max": 20
          },
          "species": "SPECIES_POLIWAG"
        },
        {
          "level": {
            "min": 20,
            "max": 20
          },
          "species": "SPECIES_POLIWAG"
        }
      ]
    },
    "super_rod": {
      "rate": 75,
      "mons": [
        {
          "level": {
            "min": 40,
            "max": 40
          },
          "species": "SPECIES_POLIWAG"
        },
        {
          "level": {
            "min": 40,
            "max": 40
          },
          "species": "SPECIES_POLIWAG"
        },
        {
          "level": {
            "min": 40,
            "max": 40
          },
          "species": "SPECIES_MAGIKARP"
        },
        {
          "level": {
            "min": 40,
            "max": 40
          },
          "species": "SPECIES_POLIWAG"
        },
        {
          "level": {
            "min": 40,
            "max": 40
          },
          "species": "SPECIES_MAGIKARP"
        }
      ]
    }
  },
  "headbutt": {}
}