{"id":"grand_lake_valor_lakefront_east_house","name":"Grand Lake Valor Lakefront East House","region":"sinnoh","source":"platinum","npcs":[{"local_id":"LOCALID_BEAUTY","graphics_id":"OBJ_EVENT_GFX_BEAUTY","x":5,"y":0,"z":3,"movement_type":"MOVEMENT_TYPE_WANDER_AROUND","trainer_type":"TRAINER_TYPE_NONE","script":1,"hidden_flag":"FLAG_HIDE_GRAND_LAKE_VALOR_LAKEFRONT_EAST_HOUSE_BEAUTY"}],"warps":[{"x":6,"y":null,"z":8,"dest_map":null,"dest_warp_id":1}],"signs":[],"coord_events":[],"tileset":"sinnoh_005"}