{"id":"322_T06GYM0101","region":"johto","source":"heartgold","script_header":"fielddata/script/scr_seq/event_T06GYM0101.h","warps":[{"x":6,"y":0,"z":22,"dest_map":"MAP_VERMILION","dest_anchor":6}],"signs":[{"x":2,"y":0,"z":13,"script_id":"_EV_scr_seq_T06GYM0101_000 + 1","type":0},{"x":4,"y":0,"z":13,"script_id":"_EV_scr_seq_T06GYM0101_001 + 1","type":0},{"x":6,"y":0,"z":13,"script_id":"_EV_scr_seq_T06GYM0101_002 + 1","type":0},{"x":8,"y":0,"z":13,"script_id":"_EV_scr_seq_T06GYM0101_003 + 1","type":0},{"x":10,"y":0,"z":13,"script_id":"_EV_scr_seq_T06GYM0101_004 + 1","type":0},{"x":2,"y":0,"z":15,"script_id":"_EV_scr_seq_T06GYM0101_005 + 1","type":0},{"x":4,"y":0,"z":15,"script_id":"_EV_scr_seq_T06GYM0101_006 + 1","type":0},{"x":6,"y":0,"z":15,"script_id":"_EV_scr_seq_T06GYM0101_007 + 1","type":0},{"x":8,"y":0,"z":15,"script_id":"_EV_scr_seq_T06GYM0101_008 + 1","type":0},{"x":10,"y":0,"z":15,"script_id":"_EV_scr_seq_T06GYM0101_009 + 1","type":0},{"x":2,"y":0,"z":17,"script_id":"_EV_scr_seq_T06GYM0101_010 + 1","type":0},{"x":4,"y":0,"z":17,"script_id":"_EV_scr_seq_T06GYM0101_011 + 1","type":0},{"x":6,"y":0,"z":17,"script_id":"_EV_scr_seq_T06GYM0101_012 + 1","type":0},{"x":8,"y":0,"z":17,"script_id":"_EV_scr_seq_T06GYM0101_013 + 1","type":0},{"x":10,"y":0,"z":17,"script_id":"_EV_scr_seq_T06GYM0101_014 + 1","type":0},{"x":4,"y":0,"z":20,"script_id":"_EV_scr_seq_T06GYM0101_025 + 1","type":0},{"x":8,"y":0,"z":20,"script_id":"_EV_scr_seq_T06GYM0101_025 + 1","type":0}],"tileset":"johto_035"}